face_mask_detector/__init__.py
face_mask_detector/command_line_interface.py
face_mask_detector/face_detector.py
face_mask_detector/file_helper.py
face_mask_detector/lib.py
face_mask_detector/logger.py
face_mask_detector/face_detector_model/__init__.py
face_mask_detector/face_detector_model/deploy.prototxt
face_mask_detector/face_detector_model/res10_300x300_ssd_iter_140000.caffemodel
face_mask_detector/face_mask_detector_model/__init__.py
face_mask_detector/face_mask_detector_model/face_mask_detector.model
face_mask_detector-0.2.3.dist-info/LICENSE
face_mask_detector-0.2.3.dist-info/METADATA
face_mask_detector-0.2.3.dist-info/WHEEL
face_mask_detector-0.2.3.dist-info/entry_points.txt
face_mask_detector-0.2.3.dist-info/top_level.txt
face_mask_detector-0.2.3.dist-info/RECORD
