Metadata-Version: 2.1
Name: face-mask-detector
Version: 0.2.3
Summary: A library and command line utility for detecting face masks in images and video streams
Home-page: https://github.com/senofsky/face-mask-detector
Author: Mark V Senofsky
Author-email: mark.v.senofsky@gmail.com
License: MIT
Keywords: face-mask-detection,face-mask,covid-19,machine-learning,computer-vision
Platform: UNKNOWN
Classifier: Programming Language :: Python :: 3.6
Classifier: Programming Language :: Python :: 3.7
Classifier: Programming Language :: Python :: 3.8
Requires-Python: >=3.6, <4
Requires-Dist: imutils (==0.5.3)
Requires-Dist: importlib-resources (==3.0.0)
Requires-Dist: numpy (==1.19.0)
Requires-Dist: opencv-python (==4.3.0.36)
Requires-Dist: tensorflow (==2.2.0)
Requires-Dist: pillow (==7.2.0)
Requires-Dist: scikit-learn (==0.23.1)
Requires-Dist: compose (==1.1.1)
Requires-Dist: matplotlib (==3.2.2)
Provides-Extra: dev
Requires-Dist: black (==19.10b0) ; extra == 'dev'
Requires-Dist: mypy (==0.770) ; extra == 'dev'
Requires-Dist: pytest (==5.4.3) ; extra == 'dev'
Requires-Dist: typing (==3.7.4.1) ; extra == 'dev'
